{
    "city": {
        "coord": {
            "lat": 37.3894,
            "lon": -122.0833
        },
        "country": "US",
        "id": 420006353,
        "name": "Mountain View"
    },
    "cnt": 96,
    "cod": "200",
    "list": [
        {
            "clouds": {
                "all": 86
            },
            "dt": 1553709600,
            "dt_txt": "2019-03-27 18:00:00",
            "main": {
                "grnd_level": 1002.193,
                "humidity": 100,
                "pressure": 1015.82,
                "sea_level": 1015.82,
                "temp": 286.44,
                "temp_kf": 0.18,
                "temp_max": 286.44,
                "temp_min": 286.258
            },
            "rain": {
                "1h": 0.812
            },
            "sys": {
                "pod": "d"
            },
            "weather": [
                {
                    "description": "light rain",
                    "icon": "10d",
                    "id": 500,
                    "main": "Rain"
                }
            ],
            "wind": {
                "deg": 202.816,
                "speed": 5.51
            }
        },
        {
            "clouds": {
                "all": 92
            },
            "dt": 1553713200,
            "dt_txt": "2019-03-27 19:00:00",
            "main": {
                "grnd_level": 1002.667,
                "humidity": 100,
                "pressure": 1016.183,
                "sea_level": 1016.183,
                "temp": 286.43,
                "temp_kf": 0.13,
                "temp_max": 286.43,
                "temp_min": 286.3
            },
            "rain": {
                "1h": 0.625
            },
            "sys": {
                "pod": "d"
            },
            "weather": [
                {
                    "description": "light rain",
                    "icon": "10d",
                    "id": 500,
                    "main": "Rain"
                }
            ],
            "wind": {
                "deg": 206.141,
                "speed": 4.84
            }
        },
        {
            "clouds": {
                "all": 94
            },
            "dt": 1553716800,
            "dt_txt": "2019-03-27 20:00:00",
            "main": {
                "grnd_level": 1003.128,
                "humidity": 100,
                "pressure": 1016.462,
                "sea_level": 1016.462,
                "temp": 286.6,
                "temp_kf": 0.09,
                "temp_max": 286.6,
                "temp_min": 286.507
            },
            "rain": {
                "1h": 0.437
            },
            "sys": {
                "pod": "d"
            },
            "weather": [
                {
                    "description": "light rain",
                    "icon": "10d",
                    "id": 500,
                    "main": "Rain"
                }
            ],
            "wind": {
                "deg": 216.201,
                "speed": 4.58
            }
        },
        {
            "clouds": {
                "all": 79
            },
            "dt": 1553720400,
            "dt_txt": "2019-03-27 21:00:00",
            "main": {
                "grnd_level": 1003.09,
                "humidity": 100,
                "pressure": 1016.441,
                "sea_level": 1016.441,
                "temp": 287.97,
                "temp_kf": 0.04,
                "temp_max": 287.97,
                "temp_min": 287.922
            },
            "rain": {
                "1h": 0.688
            },
            "sys": {
                "pod": "d"
            },
            "weather": [
                {
                    "description": "light rain",
                    "icon": "10d",
                    "id": 500,
                    "main": "Rain"
                }
            ],
            "wind": {
                "deg": 227.614,
                "speed": 5.41
            }
        },
        {
            "clouds": {
                "all": 61
            },
            "dt": 1553724000,
            "dt_txt": "2019-03-27 22:00:00",
            "main": {
                "grnd_level": 1003.042,
                "humidity": 100,
                "pressure": 1016.312,
                "sea_level": 1016.312,
                "temp": 288.27,
                "temp_kf": 0,
                "temp_max": 288.27,
                "temp_min": 288.27
            },
            "rain": {
                "1h": 0.438
            },
            "sys": {
                "pod": "d"
            },
            "weather": [
                {
                    "description": "light rain",
                    "icon": "10d",
                    "id": 500,
                    "main": "Rain"
                }
            ],
            "wind": {
                "deg": 233.008,
                "speed": 5.71
            }
        },
        {
            "clouds": {
                "all": 49
            },
            "dt": 1553727600,
            "dt_txt": "2019-03-27 23:00:00",
            "main": {
                "grnd_level": 1002.998,
                "humidity": 100,
                "pressure": 1016.293,
                "sea_level": 1016.293,
                "temp": 288.251,
                "temp_kf": 0,
                "temp_max": 288.251,
                "temp_min": 288.251
            },
            "rain": {
                "1h": 0.062
            },
            "sys": {
                "pod": "d"
            },
            "weather": [
                {
                    "description": "light rain",
                    "icon": "10d",
                    "id": 500,
                    "main": "Rain"
                }
            ],
            "wind": {
                "deg": 236.428,
                "speed": 5.79
            }
        },
        {
            "clouds": {
                "all": 41
            },
            "dt": 1553731200,
            "dt_txt": "2019-03-28 00:00:00",
            "main": {
                "grnd_level": 1003.223,
                "humidity": 100,
                "pressure": 1016.485,
                "sea_level": 1016.485,
                "temp": 287.791,
                "temp_kf": 0,
                "temp_max": 287.791,
                "temp_min": 287.791
            },
            "rain": {
                "1h": 0.062
            },
            "sys": {
                "pod": "n"
            },
            "weather": [
                {
                    "description": "light rain",
                    "icon": "10n",
                    "id": 500,
                    "main": "Rain"
                }
            ],
            "wind": {
                "deg": 239.001,
                "speed": 5.8
            }
        },
        {
            "clouds": {
                "all": 1
            },
            "dt": 1553734800,
            "dt_txt": "2019-03-28 01:00:00",
            "main": {
                "grnd_level": 1003.667,
                "humidity": 100,
                "pressure": 1016.926,
                "sea_level": 1016.926,
                "temp": 287.052,
                "temp_kf": 0,
                "temp_max": 287.052,
                "temp_min": 287.052
            },
            "sys": {
                "pod": "n"
            },
            "weather": [
                {
                    "description": "clear sky",
                    "icon": "01n",
                    "id": 800,
                    "main": "Clear"
                }
            ],
            "wind": {
                "deg": 237.97,
                "speed": 5.27
            }
        },
        {
            "clouds": {
                "all": 1
            },
            "dt": 1553738400,
            "dt_txt": "2019-03-28 02:00:00",
            "main": {
                "grnd_level": 1004.203,
                "humidity": 100,
                "pressure": 1017.562,
                "sea_level": 1017.562,
                "temp": 286.018,
                "temp_kf": 0,
                "temp_max": 286.018,
                "temp_min": 286.018
            },
            "sys": {
                "pod": "n"
            },
            "weather": [
                {
                    "description": "clear sky",
                    "icon": "01n",
                    "id": 800,
                    "main": "Clear"
                }
            ],
            "wind": {
                "deg": 230.826,
                "speed": 4.51
            }
        },
        {
            "clouds": {
                "all": 0
            },
            "dt": 1553742000,
            "dt_txt": "2019-03-28 03:00:00",
            "main": {
                "grnd_level": 1004.798,
                "humidity": 100,
                "pressure": 1018.356,
                "sea_level": 1018.356,
                "temp": 285.054,
                "temp_kf": 0,
                "temp_max": 285.054,
                "temp_min": 285.054
            },
            "sys": {
                "pod": "n"
            },
            "weather": [
                {
                    "description": "clear sky",
                    "icon": "01n",
                    "id": 800,
                    "main": "Clear"
                }
            ],
            "wind": {
                "deg": 223.133,
                "speed": 4.08
            }
        },
        {
            "clouds": {
                "all": 0
            },
            "dt": 1553745600,
            "dt_txt": "2019-03-28 04:00:00",
            "main": {
                "grnd_level": 1005.673,
                "humidity": 100,
                "pressure": 1019.469,
                "sea_level": 1019.469,
                "temp": 284.795,
                "temp_kf": 0,
                "temp_max": 284.795,
                "temp_min": 284.795
            },
            "sys": {
                "pod": "n"
            },
            "weather": [
                {
                    "description": "clear sky",
                    "icon": "01n",
                    "id": 800,
                    "main": "Clear"
                }
            ],
            "wind": {
                "deg": 219.862,
                "speed": 3.88
            }
        },
        {
            "clouds": {
                "all": 0
            },
            "dt": 1553749200,
            "dt_txt": "2019-03-28 05:00:00",
            "main": {
                "grnd_level": 1006.657,
                "humidity": 100,
                "pressure": 1020.394,
                "sea_level": 1020.394,
                "temp": 284.544,
                "temp_kf": 0,
                "temp_max": 284.544,
                "temp_min": 284.544
            },
            "sys": {
                "pod": "n"
            },
            "weather": [
                {
                    "description": "clear sky",
                    "icon": "01n",
                    "id": 800,
                    "main": "Clear"
                }
            ],
            "wind": {
                "deg": 223.743,
                "speed": 3.58
            }
        },
        {
            "clouds": {
                "all": 1
            },
            "dt": 1553752800,
            "dt_txt": "2019-03-28 06:00:00",
            "main": {
                "grnd_level": 1007.513,
                "humidity": 100,
                "pressure": 1021.219,
                "sea_level": 1021.219,
                "temp": 284.467,
                "temp_kf": 0,
                "temp_max": 284.467,
                "temp_min": 284.467
            },
            "sys": {
                "pod": "n"
            },
            "weather": [
                {
                    "description": "clear sky",
                    "icon": "01n",
                    "id": 800,
                    "main": "Clear"
                }
            ],
            "wind": {
                "deg": 218.582,
                "speed": 2.76
            }
        },
        {
            "clouds": {
                "all": 5
            },
            "dt": 1553756400,
            "dt_txt": "2019-03-28 07:00:00",
            "main": {
                "grnd_level": 1008.183,
                "humidity": 100,
                "pressure": 1021.922,
                "sea_level": 1021.922,
                "temp": 284.2,
                "temp_kf": 0,
                "temp_max": 284.2,
                "temp_min": 284.2
            },
            "rain": {
                "1h": 0.062
            },
            "sys": {
                "pod": "n"
            },
            "weather": [
                {
                    "description": "light rain",
                    "icon": "10n",
                    "id": 500,
                    "main": "Rain"
                }
            ],
            "wind": {
                "deg": 201.136,
                "speed": 2.13
            }
        },
        {
            "clouds": {
                "all": 4
            },
            "dt": 1553760000,
            "dt_txt": "2019-03-28 08:00:00",
            "main": {
                "grnd_level": 1008.803,
                "humidity": 100,
                "pressure": 1022.543,
                "sea_level": 1022.543,
                "temp": 283.9,
                "temp_kf": 0,
                "temp_max": 283.9,
                "temp_min": 283.9
            },
            "rain": {
                "1h": 0.126
            },
            "sys": {
                "pod": "n"
            },
            "weather": [
                {
                    "description": "light rain",
                    "icon": "10n",
                    "id": 500,
                    "main": "Rain"
                }
            ],
            "wind": {
                "deg": 178.624,
                "speed": 2.04
            }
        },
        {
            "clouds": {
                "all": 3
            },
            "dt": 1553763600,
            "dt_txt": "2019-03-28 09:00:00",
            "main": {
                "grnd_level": 1009.278,
                "humidity": 100,
                "pressure": 1023.004,
                "sea_level": 1023.004,
                "temp": 283.8,
                "temp_kf": 0,
                "temp_max": 283.8,
                "temp_min": 283.8
            },
            "rain": {
                "1h": 0.062
            },
            "sys": {
                "pod": "n"
            },
            "weather": [
                {
                    "description": "light rain",
                    "icon": "10n",
                    "id": 500,
                    "main": "Rain"
                }
            ],
            "wind": {
                "deg": 163.298,
                "speed": 2.36
            }
        },
        {
            "clouds": {
                "all": 5
            },
            "dt": 1553767200,
            "dt_txt": "2019-03-28 10:00:00",
            "main": {
                "grnd_level": 1009.499,
                "humidity": 100,
                "pressure": 1023.237,
                "sea_level": 1023.237,
                "temp": 283.6,
                "temp_kf": 0,
                "temp_max": 283.6,
                "temp_min": 283.6
            },
            "rain": {},
            "sys": {
                "pod": "n"
            },
            "weather": [
                {
                    "description": "clear sky",
                    "icon": "02n",
                    "id": 800,
                    "main": "Clear"
                }
            ],
            "wind": {
                "deg": 155.68,
                "speed": 2.83
            }
        },
        {
            "clouds": {
                "all": 20
            },
            "dt": 1553770800,
            "dt_txt": "2019-03-28 11:00:00",
            "main": {
                "grnd_level": 1009.529,
                "humidity": 100,
                "pressure": 1023.313,
                "sea_level": 1023.313,
                "temp": 283.433,
                "temp_kf": 0,
                "temp_max": 283.433,
                "temp_min": 283.433
            },
            "rain": {
                "1h": 0.062
            },
            "sys": {
                "pod": "n"
            },
            "weather": [
                {
                    "description": "light rain",
                    "icon": "10n",
                    "id": 500,
                    "main": "Rain"
                }
            ],
            "wind": {
                "deg": 152.732,
                "speed": 3.14
            }
        },
        {
            "clouds": {
                "all": 20
            },
            "dt": 1553774400,
            "dt_txt": "2019-03-28 12:00:00",
            "main": {
                "grnd_level": 1009.787,
                "humidity": 100,
                "pressure": 1023.573,
                "sea_level": 1023.573,
                "temp": 283.288,
                "temp_kf": 0,
                "temp_max": 283.288,
                "temp_min": 283.288
            },
            "rain": {},
            "sys": {
                "pod": "n"
            },
            "weather": [
                {
                    "description": "few clouds",
                    "icon": "02n",
                    "id": 801,
                    "main": "Clouds"
                }
            ],
            "wind": {
                "deg": 153.514,
                "speed": 3.26
            }
        },
        {
            "clouds": {
                "all": 24
            },
            "dt": 1553778000,
            "dt_txt": "2019-03-28 13:00:00",
            "main": {
                "grnd_level": 1010.154,
                "humidity": 100,
                "pressure": 1023.878,
                "sea_level": 1023.878,
                "temp": 283.2,
                "temp_kf": 0,
                "temp_max": 283.2,
                "temp_min": 283.2
            },
            "sys": {
                "pod": "n"
            },
            "weather": [
                {
                    "description": "few clouds",
                    "icon": "02n",
                    "id": 801,
                    "main": "Clouds"
                }
            ],
            "wind": {
                "deg": 154.576,
                "speed": 3.37
            }
        },
        {
            "clouds": {
                "all": 52
            },
            "dt": 1553781600,
            "dt_txt": "2019-03-28 14:00:00",
            "main": {
                "grnd_level": 1010.485,
                "humidity": 100,
                "pressure": 1024.241,
                "sea_level": 1024.241,
                "temp": 283.221,
                "temp_kf": 0,
                "temp_max": 283.221,
                "temp_min": 283.221
            },
            "sys": {
                "pod": "d"
            },
            "weather": [
                {
                    "description": "broken clouds",
                    "icon": "04d",
                    "id": 803,
                    "main": "Clouds"
                }
            ],
            "wind": {
                "deg": 155.199,
                "speed": 3.55
            }
        },
        {
            "clouds": {
                "all": 63
            },
            "dt": 1553785200,
            "dt_txt": "2019-03-28 15:00:00",
            "main": {
                "grnd_level": 1010.95,
                "humidity": 100,
                "pressure": 1024.658,
                "sea_level": 1024.658,
                "temp": 283.6,
                "temp_kf": 0,
                "temp_max": 283.6,
                "temp_min": 283.6
            },
            "sys": {
                "pod": "d"
            },
            "weather": [
                {
                    "description": "broken clouds",
                    "icon": "04d",
                    "id": 803,
                    "main": "Clouds"
                }
            ],
            "wind": {
                "deg": 157.847,
                "speed": 3.72
            }
        },
        {
            "clouds": {
                "all": 68
            },
            "dt": 1553788800,
            "dt_txt": "2019-03-28 16:00:00",
            "main": {
                "grnd_level": 1011.494,
                "humidity": 100,
                "pressure": 1025.043,
                "sea_level": 1025.043,
                "temp": 284.731,
                "temp_kf": 0,
                "temp_max": 284.731,
                "temp_min": 284.731
            },
            "sys": {
                "pod": "d"
            },
            "weather": [
                {
                    "description": "broken clouds",
                    "icon": "04d",
                    "id": 803,
                    "main": "Clouds"
                }
            ],
            "wind": {
                "deg": 167.265,
                "speed": 4.02
            }
        },
        {
            "clouds": {
                "all": 70
            },
            "dt": 1553792400,
            "dt_txt": "2019-03-28 17:00:00",
            "main": {
                "grnd_level": 1011.827,
                "humidity": 100,
                "pressure": 1025.416,
                "sea_level": 1025.416,
                "temp": 285.995,
                "temp_kf": 0,
                "temp_max": 285.995,
                "temp_min": 285.995
            },
            "sys": {
                "pod": "d"
            },
            "weather": [
                {
                    "description": "broken clouds",
                    "icon": "04d",
                    "id": 803,
                    "main": "Clouds"
                }
            ],
            "wind": {
                "deg": 178.064,
                "speed": 4.2
            }
        },
        {
            "clouds": {
                "all": 71
            },
            "dt": 1553796000,
            "dt_txt": "2019-03-28 18:00:00",
            "main": {
                "grnd_level": 1012.092,
                "humidity": 100,
                "pressure": 1025.681,
                "sea_level": 1025.681,
                "temp": 286.949,
                "temp_kf": 0,
                "temp_max": 286.949,
                "temp_min": 286.949
            },
            "sys": {
                "pod": "d"
            },
            "weather": [
                {
                    "description": "broken clouds",
                    "icon": "04d",
                    "id": 803,
                    "main": "Clouds"
                }
            ],
            "wind": {
                "deg": 192.162,
                "speed": 4.27
            }
        },
        {
            "clouds": {
                "all": 77
            },
            "dt": 1553799600,
            "dt_txt": "2019-03-28 19:00:00",
            "main": {
                "grnd_level": 1012.242,
                "humidity": 100,
                "pressure": 1025.845,
                "sea_level": 1025.845,
                "temp": 287.6,
                "temp_kf": 0,
                "temp_max": 287.6,
                "temp_min": 287.6
            },
            "rain": {
                "1h": 0.25
            },
            "sys": {
                "pod": "d"
            },
            "weather": [
                {
                    "description": "light rain",
                    "icon": "10d",
                    "id": 500,
                    "main": "Rain"
                }
            ],
            "wind": {
                "deg": 206.559,
                "speed": 4.54
            }
        },
        {
            "clouds": {
                "all": 72
            },
            "dt": 1553803200,
            "dt_txt": "2019-03-28 20:00:00",
            "main": {
                "grnd_level": 1012.27,
                "humidity": 100,
                "pressure": 1025.877,
                "sea_level": 1025.877,
                "temp": 288.1,
                "temp_kf": 0,
                "temp_max": 288.1,
                "temp_min": 288.1
            },
            "rain": {
                "1h": 0.25
            },
            "sys": {
                "pod": "d"
            },
            "weather": [
                {
                    "description": "light rain",
                    "icon": "10d",
                    "id": 500,
                    "main": "Rain"
                }
            ],
            "wind": {
                "deg": 218.177,
                "speed": 4.82
            }
        },
        {
            "clouds": {
                "all": 50
            },
            "dt": 1553806800,
            "dt_txt": "2019-03-28 21:00:00",
            "main": {
                "grnd_level": 1012.244,
                "humidity": 100,
                "pressure": 1025.799,
                "sea_level": 1025.799,
                "temp": 288.374,
                "temp_kf": 0,
                "temp_max": 288.374,
                "temp_min": 288.374
            },
            "rain": {
                "1h": 0.188
            },
            "sys": {
                "pod": "d"
            },
            "weather": [
                {
                    "description": "light rain",
                    "icon": "10d",
                    "id": 500,
                    "main": "Rain"
                }
            ],
            "wind": {
                "deg": 226.407,
                "speed": 5.21
            }
        },
        {
            "clouds": {
                "all": 49
            },
            "dt": 1553810400,
            "dt_txt": "2019-03-28 22:00:00",
            "main": {
                "grnd_level": 1011.894,
                "humidity": 100,
                "pressure": 1025.427,
                "sea_level": 1025.427,
                "temp": 288.226,
                "temp_kf": 0,
                "temp_max": 288.226,
                "temp_min": 288.226
            },
            "rain": {
                "1h": 0.124
            },
            "sys": {
                "pod": "d"
            },
            "weather": [
                {
                    "description": "light rain",
                    "icon": "10d",
                    "id": 500,
                    "main": "Rain"
                }
            ],
            "wind": {
                "deg": 233.036,
                "speed": 5.37
            }
        },
        {
            "clouds": {
                "all": 40
            },
            "dt": 1553814000,
            "dt_txt": "2019-03-28 23:00:00",
            "main": {
                "grnd_level": 1011.533,
                "humidity": 100,
                "pressure": 1025.102,
                "sea_level": 1025.102,
                "temp": 288.1,
                "temp_kf": 0,
                "temp_max": 288.1,
                "temp_min": 288.1
            },
            "rain": {
                "1h": 0.063
            },
            "sys": {
                "pod": "d"
            },
            "weather": [
                {
                    "description": "light rain",
                    "icon": "10d",
                    "id": 500,
                    "main": "Rain"
                }
            ],
            "wind": {
                "deg": 238.27,
                "speed": 5.23
            }
        },
        {
            "clouds": {
                "all": 34
            },
            "dt": 1553817600,
            "dt_txt": "2019-03-29 00:00:00",
            "main": {
                "grnd_level": 1011.478,
                "humidity": 100,
                "pressure": 1025.062,
                "sea_level": 1025.062,
                "temp": 287.7,
                "temp_kf": 0,
                "temp_max": 287.7,
                "temp_min": 287.7
            },
            "sys": {
                "pod": "n"
            },
            "weather": [
                {
                    "description": "scattered clouds",
                    "icon": "03n",
                    "id": 802,
                    "main": "Clouds"
                }
            ],
            "wind": {
                "deg": 243.083,
                "speed": 4.88
            }
        },
        {
            "clouds": {
                "all": 4
            },
            "dt": 1553821200,
            "dt_txt": "2019-03-29 01:00:00",
            "main": {
                "grnd_level": 1011.624,
                "humidity": 100,
                "pressure": 1025.148,
                "sea_level": 1025.148,
                "temp": 287.08,
                "temp_kf": 0,
                "temp_max": 287.08,
                "temp_min": 287.08
            },
            "sys": {
                "pod": "n"
            },
            "weather": [
                {
                    "description": "clear sky",
                    "icon": "02n",
                    "id": 800,
                    "main": "Clear"
                }
            ],
            "wind": {
                "deg": 246.472,
                "speed": 4.36
            }
        },
        {
            "clouds": {
                "all": 2
            },
            "dt": 1553824800,
            "dt_txt": "2019-03-29 02:00:00",
            "main": {
                "grnd_level": 1011.879,
                "humidity": 100,
                "pressure": 1025.433,
                "sea_level": 1025.433,
                "temp": 286.139,
                "temp_kf": 0,
                "temp_max": 286.139,
                "temp_min": 286.139
            },
            "sys": {
                "pod": "n"
            },
            "weather": [
                {
                    "description": "clear sky",
                    "icon": "02n",
                    "id": 800,
                    "main": "Clear"
                }
            ],
            "wind": {
                "deg": 247.193,
                "speed": 3.42
            }
        },
        {
            "clouds": {
                "all": 2
            },
            "dt": 1553828400,
            "dt_txt": "2019-03-29 03:00:00",
            "main": {
                "grnd_level": 1012.204,
                "humidity": 100,
                "pressure": 1025.802,
                "sea_level": 1025.802,
                "temp": 285.065,
                "temp_kf": 0,
                "temp_max": 285.065,
                "temp_min": 285.065
            },
            "sys": {
                "pod": "n"
            },
            "weather": [
                {
                    "description": "clear sky",
                    "icon": "02n",
                    "id": 800,
                    "main": "Clear"
                }
            ],
            "wind": {
                "deg": 243.012,
                "speed": 2.79
            }
        },
        {
            "clouds": {
                "all": 1
            },
            "dt": 1553832000,
            "dt_txt": "2019-03-29 04:00:00",
            "main": {
                "grnd_level": 1012.8,
                "humidity": 100,
                "pressure": 1026.4,
                "sea_level": 1026.4,
                "temp": 284.678,
                "temp_kf": 0,
                "temp_max": 284.678,
                "temp_min": 284.678
            },
            "sys": {
                "pod": "n"
            },
            "weather": [
                {
                    "description": "clear sky",
                    "icon": "01n",
                    "id": 800,
                    "main": "Clear"
                }
            ],
            "wind": {
                "deg": 233.631,
                "speed": 2.22
            }
        },
        {
            "clouds": {
                "all": 1
            },
            "dt": 1553835600,
            "dt_txt": "2019-03-29 05:00:00",
            "main": {
                "grnd_level": 1013.411,
                "humidity": 100,
                "pressure": 1027.093,
                "sea_level": 1027.093,
                "temp": 284.382,
                "temp_kf": 0,
                "temp_max": 284.382,
                "temp_min": 284.382
            },
            "sys": {
                "pod": "n"
            },
            "weather": [
                {
                    "description": "clear sky",
                    "icon": "01n",
                    "id": 800,
                    "main": "Clear"
                }
            ],
            "wind": {
                "deg": 222.163,
                "speed": 1.74
            }
        },
        {
            "clouds": {
                "all": 0
            },
            "dt": 1553839200,
            "dt_txt": "2019-03-29 06:00:00",
            "main": {
                "grnd_level": 1013.785,
                "humidity": 100,
                "pressure": 1027.555,
                "sea_level": 1027.555,
                "temp": 284.025,
                "temp_kf": 0,
                "temp_max": 284.025,
                "temp_min": 284.025
            },
            "sys": {
                "pod": "n"
            },
            "weather": [
                {
                    "description": "clear sky",
                    "icon": "01n",
                    "id": 800,
                    "main": "Clear"
                }
            ],
            "wind": {
                "deg": 210.944,
                "speed": 1.48
            }
        },
        {
            "clouds": {
                "all": 0
            },
            "dt": 1553842800,
            "dt_txt": "2019-03-29 07:00:00",
            "main": {
                "grnd_level": 1013.768,
                "humidity": 100,
                "pressure": 1027.564,
                "sea_level": 1027.564,
                "temp": 283.7,
                "temp_kf": 0,
                "temp_max": 283.7,
                "temp_min": 283.7
            },
            "sys": {
                "pod": "n"
            },
            "weather": [
                {
                    "description": "clear sky",
                    "icon": "01n",
                    "id": 800,
                    "main": "Clear"
                }
            ],
            "wind": {
                "deg": 200.304,
                "speed": 1.44
            }
        },
        {
            "clouds": {
                "all": 0
            },
            "dt": 1553846400,
            "dt_txt": "2019-03-29 08:00:00",
            "main": {
                "grnd_level": 1013.797,
                "humidity": 100,
                "pressure": 1027.561,
                "sea_level": 1027.561,
                "temp": 283.574,
                "temp_kf": 0,
                "temp_max": 283.574,
                "temp_min": 283.574
            },
            "sys": {
                "pod": "n"
            },
            "weather": [
                {
                    "description": "clear sky",
                    "icon": "01n",
                    "id": 800,
                    "main": "Clear"
                }
            ],
            "wind": {
                "deg": 203.562,
                "speed": 1.37
            }
        },
        {
            "clouds": {
                "all": 0
            },
            "dt": 1553850000,
            "dt_txt": "2019-03-29 09:00:00",
            "main": {
                "grnd_level": 1014.055,
                "humidity": 100,
                "pressure": 1027.843,
                "sea_level": 1027.843,
                "temp": 283.351,
                "temp_kf": 0,
                "temp_max": 283.351,
                "temp_min": 283.351
            },
            "sys": {
                "pod": "n"
            },
            "weather": [
                {
                    "description": "clear sky",
                    "icon": "01n",
                    "id": 800,
                    "main": "Clear"
                }
            ],
            "wind": {
                "deg": 215.22,
                "speed": 1.32
            }
        },
        {
            "clouds": {
                "all": 2
            },
            "dt": 1553853600,
            "dt_txt": "2019-03-29 10:00:00",
            "main": {
                "grnd_level": 1014.181,
                "humidity": 100,
                "pressure": 1027.926,
                "sea_level": 1027.926,
                "temp": 283.225,
                "temp_kf": 0,
                "temp_max": 283.225,
                "temp_min": 283.225
            },
            "sys": {
                "pod": "n"
            },
            "weather": [
                {
                    "description": "clear sky",
                    "icon": "02n",
                    "id": 800,
                    "main": "Clear"
                }
            ],
            "wind": {
                "deg": 219.003,
                "speed": 1.28
            }
        },
        {
            "clouds": {
                "all": 15
            },
            "dt": 1553857200,
            "dt_txt": "2019-03-29 11:00:00",
            "main": {
                "grnd_level": 1014.011,
                "humidity": 100,
                "pressure": 1027.733,
                "sea_level": 1027.733,
                "temp": 283.736,
                "temp_kf": 0,
                "temp_max": 283.736,
                "temp_min": 283.736
            },
            "rain": {
                "1h": 0.062
            },
            "sys": {
                "pod": "n"
            },
            "weather": [
                {
                    "description": "light rain",
                    "icon": "10n",
                    "id": 500,
                    "main": "Rain"
                }
            ],
            "wind": {
                "deg": 213.73,
                "speed": 1.21
            }
        },
        {
            "clouds": {
                "all": 26
            },
            "dt": 1553860800,
            "dt_txt": "2019-03-29 12:00:00",
            "main": {
                "grnd_level": 1013.788,
                "humidity": 100,
                "pressure": 1027.527,
                "sea_level": 1027.527,
                "temp": 283.688,
                "temp_kf": 0,
                "temp_max": 283.688,
                "temp_min": 283.688
            },
            "rain": {
                "1h": 0.188
            },
            "sys": {
                "pod": "n"
            },
            "weather": [
                {
                    "description": "light rain",
                    "icon": "10n",
                    "id": 500,
                    "main": "Rain"
                }
            ],
            "wind": {
                "deg": 198.819,
                "speed": 0.94
            }
        },
        {
            "clouds": {
                "all": 83
            },
            "dt": 1553864400,
            "dt_txt": "2019-03-29 13:00:00",
            "main": {
                "grnd_level": 1013.62,
                "humidity": 100,
                "pressure": 1027.396,
                "sea_level": 1027.396,
                "temp": 283.651,
                "temp_kf": 0,
                "temp_max": 283.651,
                "temp_min": 283.651
            },
            "rain": {
                "1h": 0.125
            },
            "sys": {
                "pod": "n"
            },
            "weather": [
                {
                    "description": "light rain",
                    "icon": "10n",
                    "id": 500,
                    "main": "Rain"
                }
            ],
            "wind": {
                "deg": 175.201,
                "speed": 1.09
            }
        },
        {
            "clouds": {
                "all": 56
            },
            "dt": 1553868000,
            "dt_txt": "2019-03-29 14:00:00",
            "main": {
                "grnd_level": 1013.662,
                "humidity": 100,
                "pressure": 1027.457,
                "sea_level": 1027.457,
                "temp": 283.145,
                "temp_kf": 0,
                "temp_max": 283.145,
                "temp_min": 283.145
            },
            "rain": {},
            "sys": {
                "pod": "d"
            },
            "weather": [
                {
                    "description": "broken clouds",
                    "icon": "04d",
                    "id": 803,
                    "main": "Clouds"
                }
            ],
            "wind": {
                "deg": 153.887,
                "speed": 0.85
            }
        },
        {
            "clouds": {
                "all": 38
            },
            "dt": 1553871600,
            "dt_txt": "2019-03-29 15:00:00",
            "main": {
                "grnd_level": 1014.095,
                "humidity": 100,
                "pressure": 1027.822,
                "sea_level": 1027.822,
                "temp": 283.674,
                "temp_kf": 0,
                "temp_max": 283.674,
                "temp_min": 283.674
            },
            "rain": {},
            "sys": {
                "pod": "d"
            },
            "weather": [
                {
                    "description": "scattered clouds",
                    "icon": "03d",
                    "id": 802,
                    "main": "Clouds"
                }
            ],
            "wind": {
                "deg": 103.462,
                "speed": 0.53
            }
        },
        {
            "clouds": {
                "all": 28
            },
            "dt": 1553875200,
            "dt_txt": "2019-03-29 16:00:00",
            "main": {
                "grnd_level": 1014.796,
                "humidity": 100,
                "pressure": 1028.223,
                "sea_level": 1028.223,
                "temp": 285.326,
                "temp_kf": 0,
                "temp_max": 285.326,
                "temp_min": 285.326
            },
            "rain": {},
            "sys": {
                "pod": "d"
            },
            "weather": [
                {
                    "description": "scattered clouds",
                    "icon": "03d",
                    "id": 802,
                    "main": "Clouds"
                }
            ],
            "wind": {
                "deg": 0.5,
                "speed": 0.69
            }
        },
        {
            "clouds": {
                "all": 23
            },
            "dt": 1553878800,
            "dt_txt": "2019-03-29 17:00:00",
            "main": {
                "grnd_level": 1014.967,
                "humidity": 100,
                "pressure": 1028.38,
                "sea_level": 1028.38,
                "temp": 286.5,
                "temp_kf": 0,
                "temp_max": 286.5,
                "temp_min": 286.5
            },
            "rain": {},
            "sys": {
                "pod": "d"
            },
            "weather": [
                {
                    "description": "few clouds",
                    "icon": "02d",
                    "id": 801,
                    "main": "Clouds"
                }
            ],
            "wind": {
                "deg": 337.194,
                "speed": 1.42
            }
        },
        {
            "clouds": {
                "all": 19
            },
            "dt": 1553882400,
            "dt_txt": "2019-03-29 18:00:00",
            "main": {
                "grnd_level": 1015.161,
                "humidity": 100,
                "pressure": 1028.359,
                "sea_level": 1028.359,
                "temp": 287.445,
                "temp_kf": 0,
                "temp_max": 287.445,
                "temp_min": 287.445
            },
            "rain": {},
            "sys": {
                "pod": "d"
            },
            "weather": [
                {
                    "description": "few clouds",
                    "icon": "02d",
                    "id": 801,
                    "main": "Clouds"
                }
            ],
            "wind": {
                "deg": 322.011,
                "speed": 2.11
            }
        },
        {
            "clouds": {
                "all": 0
            },
            "dt": 1553886000,
            "dt_txt": "2019-03-29 19:00:00",
            "main": {
                "grnd_level": 1014.827,
                "humidity": 100,
                "pressure": 1028.067,
                "sea_level": 1028.067,
                "temp": 288.149,
                "temp_kf": 0,
                "temp_max": 288.149,
                "temp_min": 288.149
            },
            "sys": {
                "pod": "d"
            },
            "weather": [
                {
                    "description": "clear sky",
                    "icon": "01d",
                    "id": 800,
                    "main": "Clear"
                }
            ],
            "wind": {
                "deg": 312.395,
                "speed": 2.79
            }
        },
        {
            "clouds": {
                "all": 0
            },
            "dt": 1553889600,
            "dt_txt": "2019-03-29 20:00:00",
            "main": {
                "grnd_level": 1014.411,
                "humidity": 100,
                "pressure": 1027.704,
                "sea_level": 1027.704,
                "temp": 288.8,
                "temp_kf": 0,
                "temp_max": 288.8,
                "temp_min": 288.8
            },
            "sys": {
                "pod": "d"
            },
            "weather": [
                {
                    "description": "clear sky",
                    "icon": "01d",
                    "id": 800,
                    "main": "Clear"
                }
            ],
            "wind": {
                "deg": 304.036,
                "speed": 3.49
            }
        },
        {
            "clouds": {
                "all": 0
            },
            "dt": 1553893200,
            "dt_txt": "2019-03-29 21:00:00",
            "main": {
                "grnd_level": 1014.125,
                "humidity": 100,
                "pressure": 1027.397,
                "sea_level": 1027.397,
                "temp": 289.264,
                "temp_kf": 0,
                "temp_max": 289.264,
                "temp_min": 289.264
            },
            "sys": {
                "pod": "d"
            },
            "weather": [
                {
                    "description": "clear sky",
                    "icon": "01d",
                    "id": 800,
                    "main": "Clear"
                }
            ],
            "wind": {
                "deg": 299.416,
                "speed": 4.02
            }
        },
        {
            "clouds": {
                "all": 0
            },
            "dt": 1553896800,
            "dt_txt": "2019-03-29 22:00:00",
            "main": {
                "grnd_level": 1013.687,
                "humidity": 100,
                "pressure": 1027.036,
                "sea_level": 1027.036,
                "temp": 289.196,
                "temp_kf": 0,
                "temp_max": 289.196,
                "temp_min": 289.196
            },
            "sys": {
                "pod": "d"
            },
            "weather": [
                {
                    "description": "clear sky",
                    "icon": "01d",
                    "id": 800,
                    "main": "Clear"
                }
            ],
            "wind": {
                "deg": 295.606,
                "speed": 4.36
            }
        },
        {
            "clouds": {
                "all": 1
            },
            "dt": 1553900400,
            "dt_txt": "2019-03-29 23:00:00",
            "main": {
                "grnd_level": 1013.311,
                "humidity": 100,
                "pressure": 1026.627,
                "sea_level": 1026.627,
                "temp": 288.743,
                "temp_kf": 0,
                "temp_max": 288.743,
                "temp_min": 288.743
            },
            "sys": {
                "pod": "d"
            },
            "weather": [
                {
                    "description": "clear sky",
                    "icon": "01d",
                    "id": 800,
                    "main": "Clear"
                }
            ],
            "wind": {
                "deg": 297.713,
                "speed": 4.53
            }
        },
        {
            "clouds": {
                "all": 0
            },
            "dt": 1553904000,
            "dt_txt": "2019-03-30 00:00:00",
            "main": {
                "grnd_level": 1013.019,
                "humidity": 100,
                "pressure": 1026.347,
                "sea_level": 1026.347,
                "temp": 288.161,
                "temp_kf": 0,
                "temp_max": 288.161,
                "temp_min": 288.161
            },
            "sys": {
                "pod": "n"
            },
            "weather": [
                {
                    "description": "clear sky",
                    "icon": "01n",
                    "id": 800,
                    "main": "Clear"
                }
            ],
            "wind": {
                "deg": 299.009,
                "speed": 4.51
            }
        },
        {
            "clouds": {
                "all": 0
            },
            "dt": 1553907600,
            "dt_txt": "2019-03-30 01:00:00",
            "main": {
                "grnd_level": 1013.066,
                "humidity": 100,
                "pressure": 1026.38,
                "sea_level": 1026.38,
                "temp": 287.33,
                "temp_kf": 0,
                "temp_max": 287.33,
                "temp_min": 287.33
            },
            "sys": {
                "pod": "n"
            },
            "weather": [
                {
                    "description": "clear sky",
                    "icon": "01n",
                    "id": 800,
                    "main": "Clear"
                }
            ],
            "wind": {
                "deg": 298.862,
                "speed": 4.42
            }
        },
        {
            "clouds": {
                "all": 0
            },
            "dt": 1553911200,
            "dt_txt": "2019-03-30 02:00:00",
            "main": {
                "grnd_level": 1013.382,
                "humidity": 100,
                "pressure": 1026.69,
                "sea_level": 1026.69,
                "temp": 286.149,
                "temp_kf": 0,
                "temp_max": 286.149,
                "temp_min": 286.149
            },
            "sys": {
                "pod": "n"
            },
            "weather": [
                {
                    "description": "clear sky",
                    "icon": "01n",
                    "id": 800,
                    "main": "Clear"
                }
            ],
            "wind": {
                "deg": 296.475,
                "speed": 3.97
            }
        },
        {
            "clouds": {
                "all": 0
            },
            "dt": 1553914800,
            "dt_txt": "2019-03-30 03:00:00",
            "main": {
                "grnd_level": 1013.872,
                "humidity": 100,
                "pressure": 1027.124,
                "sea_level": 1027.124,
                "temp": 284.95,
                "temp_kf": 0,
                "temp_max": 284.95,
                "temp_min": 284.95
            },
            "sys": {
                "pod": "n"
            },
            "weather": [
                {
                    "description": "clear sky",
                    "icon": "01n",
                    "id": 800,
                    "main": "Clear"
                }
            ],
            "wind": {
                "deg": 296.632,
                "speed": 3.81
            }
        },
        {
            "clouds": {
                "all": 9
            },
            "dt": 1553918400,
            "dt_txt": "2019-03-30 04:00:00",
            "main": {
                "grnd_level": 1014.29,
                "humidity": 100,
                "pressure": 1027.603,
                "sea_level": 1027.603,
                "temp": 284.407,
                "temp_kf": 0,
                "temp_max": 284.407,
                "temp_min": 284.407
            },
            "sys": {
                "pod": "n"
            },
            "weather": [
                {
                    "description": "clear sky",
                    "icon": "02n",
                    "id": 800,
                    "main": "Clear"
                }
            ],
            "wind": {
                "deg": 309.538,
                "speed": 3.13
            }
        },
        {
            "clouds": {
                "all": 21
            },
            "dt": 1553922000,
            "dt_txt": "2019-03-30 05:00:00",
            "main": {
                "grnd_level": 1014.464,
                "humidity": 100,
                "pressure": 1027.86,
                "sea_level": 1027.86,
                "temp": 284.095,
                "temp_kf": 0,
                "temp_max": 284.095,
                "temp_min": 284.095
            },
            "sys": {
                "pod": "n"
            },
            "weather": [
                {
                    "description": "few clouds",
                    "icon": "02n",
                    "id": 801,
                    "main": "Clouds"
                }
            ],
            "wind": {
                "deg": 318.251,
                "speed": 2.52
            }
        },
        {
            "clouds": {
                "all": 19
            },
            "dt": 1553925600,
            "dt_txt": "2019-03-30 06:00:00",
            "main": {
                "grnd_level": 1014.417,
                "humidity": 100,
                "pressure": 1027.676,
                "sea_level": 1027.676,
                "temp": 283.877,
                "temp_kf": 0,
                "temp_max": 283.877,
                "temp_min": 283.877
            },
            "sys": {
                "pod": "n"
            },
            "weather": [
                {
                    "description": "few clouds",
                    "icon": "02n",
                    "id": 801,
                    "main": "Clouds"
                }
            ],
            "wind": {
                "deg": 316.305,
                "speed": 2.24
            }
        },
        {
            "clouds": {
                "all": 19
            },
            "dt": 1553929200,
            "dt_txt": "2019-03-30 07:00:00",
            "main": {
                "grnd_level": 1013.701,
                "humidity": 100,
                "pressure": 1027.096,
                "sea_level": 1027.096,
                "temp": 283.619,
                "temp_kf": 0,
                "temp_max": 283.619,
                "temp_min": 283.619
            },
            "sys": {
                "pod": "n"
            },
            "weather": [
                {
                    "description": "few clouds",
                    "icon": "02n",
                    "id": 801,
                    "main": "Clouds"
                }
            ],
            "wind": {
                "deg": 329.231,
                "speed": 1.71
            }
        },
        {
            "clouds": {
                "all": 9
            },
            "dt": 1553932800,
            "dt_txt": "2019-03-30 08:00:00",
            "main": {
                "grnd_level": 1013.181,
                "humidity": 100,
                "pressure": 1026.464,
                "sea_level": 1026.464,
                "temp": 283.277,
                "temp_kf": 0,
                "temp_max": 283.277,
                "temp_min": 283.277
            },
            "sys": {
                "pod": "n"
            },
            "weather": [
                {
                    "description": "clear sky",
                    "icon": "02n",
                    "id": 800,
                    "main": "Clear"
                }
            ],
            "wind": {
                "deg": 330.103,
                "speed": 1.63
            }
        },
        {
            "clouds": {
                "all": 10
            },
            "dt": 1553936400,
            "dt_txt": "2019-03-30 09:00:00",
            "main": {
                "grnd_level": 1012.695,
                "humidity": 100,
                "pressure": 1025.955,
                "sea_level": 1025.955,
                "temp": 283.104,
                "temp_kf": 0,
                "temp_max": 283.104,
                "temp_min": 283.104
            },
            "sys": {
                "pod": "n"
            },
            "weather": [
                {
                    "description": "clear sky",
                    "icon": "02n",
                    "id": 800,
                    "main": "Clear"
                }
            ],
            "wind": {
                "deg": 338.271,
                "speed": 1.62
            }
        },
        {
            "clouds": {
                "all": 16
            },
            "dt": 1553940000,
            "dt_txt": "2019-03-30 10:00:00",
            "main": {
                "grnd_level": 1012.092,
                "humidity": 100,
                "pressure": 1025.47,
                "sea_level": 1025.47,
                "temp": 282.804,
                "temp_kf": 0,
                "temp_max": 282.804,
                "temp_min": 282.804
            },
            "sys": {
                "pod": "n"
            },
            "weather": [
                {
                    "description": "few clouds",
                    "icon": "02n",
                    "id": 801,
                    "main": "Clouds"
                }
            ],
            "wind": {
                "deg": 352.233,
                "speed": 1.32
            }
        },
        {
            "clouds": {
                "all": 15
            },
            "dt": 1553943600,
            "dt_txt": "2019-03-30 11:00:00",
            "main": {
                "grnd_level": 1011.686,
                "humidity": 100,
                "pressure": 1025.051,
                "sea_level": 1025.051,
                "temp": 282.504,
                "temp_kf": 0,
                "temp_max": 282.504,
                "temp_min": 282.504
            },
            "sys": {
                "pod": "n"
            },
            "weather": [
                {
                    "description": "few clouds",
                    "icon": "02n",
                    "id": 801,
                    "main": "Clouds"
                }
            ],
            "wind": {
                "deg": 1.212,
                "speed": 1.28
            }
        },
        {
            "clouds": {
                "all": 15
            },
            "dt": 1553947200,
            "dt_txt": "2019-03-30 12:00:00",
            "main": {
                "grnd_level": 1011.615,
                "humidity": 100,
                "pressure": 1024.871,
                "sea_level": 1024.871,
                "temp": 282.405,
                "temp_kf": 0,
                "temp_max": 282.405,
                "temp_min": 282.405
            },
            "sys": {
                "pod": "n"
            },
            "weather": [
                {
                    "description": "few clouds",
                    "icon": "02n",
                    "id": 801,
                    "main": "Clouds"
                }
            ],
            "wind": {
                "deg": 4.192,
                "speed": 1.38
            }
        },
        {
            "clouds": {
                "all": 0
            },
            "dt": 1553950800,
            "dt_txt": "2019-03-30 13:00:00",
            "main": {
                "grnd_level": 1011.792,
                "humidity": 100,
                "pressure": 1024.968,
                "sea_level": 1024.968,
                "temp": 282.231,
                "temp_kf": 0,
                "temp_max": 282.231,
                "temp_min": 282.231
            },
            "sys": {
                "pod": "n"
            },
            "weather": [
                {
                    "description": "clear sky",
                    "icon": "01n",
                    "id": 800,
                    "main": "Clear"
                }
            ],
            "wind": {
                "deg": 5.252,
                "speed": 1.45
            }
        },
        {
            "clouds": {
                "all": 0
            },
            "dt": 1553954400,
            "dt_txt": "2019-03-30 14:00:00",
            "main": {
                "grnd_level": 1012.106,
                "humidity": 100,
                "pressure": 1025.284,
                "sea_level": 1025.284,
                "temp": 282.048,
                "temp_kf": 0,
                "temp_max": 282.048,
                "temp_min": 282.048
            },
            "sys": {
                "pod": "d"
            },
            "weather": [
                {
                    "description": "clear sky",
                    "icon": "01d",
                    "id": 800,
                    "main": "Clear"
                }
            ],
            "wind": {
                "deg": 10.203,
                "speed": 1.41
            }
        },
        {
            "clouds": {
                "all": 8
            },
            "dt": 1553958000,
            "dt_txt": "2019-03-30 15:00:00",
            "main": {
                "grnd_level": 1012.457,
                "humidity": 100,
                "pressure": 1025.572,
                "sea_level": 1025.572,
                "temp": 283.1,
                "temp_kf": 0,
                "temp_max": 283.1,
                "temp_min": 283.1
            },
            "sys": {
                "pod": "d"
            },
            "weather": [
                {
                    "description": "clear sky",
                    "icon": "02d",
                    "id": 800,
                    "main": "Clear"
                }
            ],
            "wind": {
                "deg": 20.764,
                "speed": 1.32
            }
        },
        {
            "clouds": {
                "all": 11
            },
            "dt": 1553961600,
            "dt_txt": "2019-03-30 16:00:00",
            "main": {
                "grnd_level": 1012.657,
                "humidity": 100,
                "pressure": 1025.573,
                "sea_level": 1025.573,
                "temp": 284.852,
                "temp_kf": 0,
                "temp_max": 284.852,
                "temp_min": 284.852
            },
            "sys": {
                "pod": "d"
            },
            "weather": [
                {
                    "description": "few clouds",
                    "icon": "02d",
                    "id": 801,
                    "main": "Clouds"
                }
            ],
            "wind": {
                "deg": 22.262,
                "speed": 1.69
            }
        },
        {
            "clouds": {
                "all": 13
            },
            "dt": 1553965200,
            "dt_txt": "2019-03-30 17:00:00",
            "main": {
                "grnd_level": 1012.698,
                "humidity": 100,
                "pressure": 1025.603,
                "sea_level": 1025.603,
                "temp": 286.7,
                "temp_kf": 0,
                "temp_max": 286.7,
                "temp_min": 286.7
            },
            "sys": {
                "pod": "d"
            },
            "weather": [
                {
                    "description": "few clouds",
                    "icon": "02d",
                    "id": 801,
                    "main": "Clouds"
                }
            ],
            "wind": {
                "deg": 20.985,
                "speed": 2.11
            }
        },
        {
            "clouds": {
                "all": 16
            },
            "dt": 1553968800,
            "dt_txt": "2019-03-30 18:00:00",
            "main": {
                "grnd_level": 1012.712,
                "humidity": 100,
                "pressure": 1025.72,
                "sea_level": 1025.72,
                "temp": 288.221,
                "temp_kf": 0,
                "temp_max": 288.221,
                "temp_min": 288.221
            },
            "sys": {
                "pod": "d"
            },
            "weather": [
                {
                    "description": "few clouds",
                    "icon": "02d",
                    "id": 801,
                    "main": "Clouds"
                }
            ],
            "wind": {
                "deg": 12.934,
                "speed": 2.53
            }
        },
        {
            "clouds": {
                "all": 51
            },
            "dt": 1553972400,
            "dt_txt": "2019-03-30 19:00:00",
            "main": {
                "grnd_level": 1012.721,
                "humidity": 100,
                "pressure": 1025.708,
                "sea_level": 1025.708,
                "temp": 289.507,
                "temp_kf": 0,
                "temp_max": 289.507,
                "temp_min": 289.507
            },
            "sys": {
                "pod": "d"
            },
            "weather": [
                {
                    "description": "broken clouds",
                    "icon": "04d",
                    "id": 803,
                    "main": "Clouds"
                }
            ],
            "wind": {
                "deg": 358.57,
                "speed": 3.05
            }
        },
        {
            "clouds": {
                "all": 53
            },
            "dt": 1553976000,
            "dt_txt": "2019-03-30 20:00:00",
            "main": {
                "grnd_level": 1012.311,
                "humidity": 100,
                "pressure": 1025.351,
                "sea_level": 1025.351,
                "temp": 290.481,
                "temp_kf": 0,
                "temp_max": 290.481,
                "temp_min": 290.481
            },
            "sys": {
                "pod": "d"
            },
            "weather": [
                {
                    "description": "broken clouds",
                    "icon": "04d",
                    "id": 803,
                    "main": "Clouds"
                }
            ],
            "wind": {
                "deg": 344.278,
                "speed": 3.21
            }
        },
        {
            "clouds": {
                "all": 42
            },
            "dt": 1553979600,
            "dt_txt": "2019-03-30 21:00:00",
            "main": {
                "grnd_level": 1011.687,
                "humidity": 100,
                "pressure": 1024.767,
                "sea_level": 1024.767,
                "temp": 291.131,
                "temp_kf": 0,
                "temp_max": 291.131,
                "temp_min": 291.131
            },
            "sys": {
                "pod": "d"
            },
            "weather": [
                {
                    "description": "scattered clouds",
                    "icon": "03d",
                    "id": 802,
                    "main": "Clouds"
                }
            ],
            "wind": {
                "deg": 333.603,
                "speed": 3.35
            }
        },
        {
            "clouds": {
                "all": 42
            },
            "dt": 1553983200,
            "dt_txt": "2019-03-30 22:00:00",
            "main": {
                "grnd_level": 1011.05,
                "humidity": 100,
                "pressure": 1024.056,
                "sea_level": 1024.056,
                "temp": 291.431,
                "temp_kf": 0,
                "temp_max": 291.431,
                "temp_min": 291.431
            },
            "sys": {
                "pod": "d"
            },
            "weather": [
                {
                    "description": "scattered clouds",
                    "icon": "03d",
                    "id": 802,
                    "main": "Clouds"
                }
            ],
            "wind": {
                "deg": 319.735,
                "speed": 3.64
            }
        },
        {
            "clouds": {
                "all": 43
            },
            "dt": 1553986800,
            "dt_txt": "2019-03-30 23:00:00",
            "main": {
                "grnd_level": 1010.505,
                "humidity": 100,
                "pressure": 1023.473,
                "sea_level": 1023.473,
                "temp": 291.045,
                "temp_kf": 0,
                "temp_max": 291.045,
                "temp_min": 291.045
            },
            "sys": {
                "pod": "d"
            },
            "weather": [
                {
                    "description": "scattered clouds",
                    "icon": "03d",
                    "id": 802,
                    "main": "Clouds"
                }
            ],
            "wind": {
                "deg": 311.347,
                "speed": 3.88
            }
        },
        {
            "clouds": {
                "all": 46
            },
            "dt": 1553990400,
            "dt_txt": "2019-03-31 00:00:00",
            "main": {
                "grnd_level": 1010.061,
                "humidity": 100,
                "pressure": 1023.071,
                "sea_level": 1023.071,
                "temp": 290.505,
                "temp_kf": 0,
                "temp_max": 290.505,
                "temp_min": 290.505
            },
            "sys": {
                "pod": "n"
            },
            "weather": [
                {
                    "description": "scattered clouds",
                    "icon": "03n",
                    "id": 802,
                    "main": "Clouds"
                }
            ],
            "wind": {
                "deg": 307.293,
                "speed": 3.6
            }
        },
        {
            "clouds": {
                "all": 46
            },
            "dt": 1553994000,
            "dt_txt": "2019-03-31 01:00:00",
            "main": {
                "grnd_level": 1009.931,
                "humidity": 100,
                "pressure": 1022.991,
                "sea_level": 1022.991,
                "temp": 289.589,
                "temp_kf": 0,
                "temp_max": 289.589,
                "temp_min": 289.589
            },
            "sys": {
                "pod": "n"
            },
            "weather": [
                {
                    "description": "scattered clouds",
                    "icon": "03n",
                    "id": 802,
                    "main": "Clouds"
                }
            ],
            "wind": {
                "deg": 304.143,
                "speed": 3.54
            }
        },
        {
            "clouds": {
                "all": 24
            },
            "dt": 1553997600,
            "dt_txt": "2019-03-31 02:00:00",
            "main": {
                "grnd_level": 1010.412,
                "humidity": 100,
                "pressure": 1023.357,
                "sea_level": 1023.357,
                "temp": 288.115,
                "temp_kf": 0,
                "temp_max": 288.115,
                "temp_min": 288.115
            },
            "sys": {
                "pod": "n"
            },
            "weather": [
                {
                    "description": "few clouds",
                    "icon": "02n",
                    "id": 801,
                    "main": "Clouds"
                }
            ],
            "wind": {
                "deg": 300.364,
                "speed": 3.42
            }
        },
        {
            "clouds": {
                "all": 16
            },
            "dt": 1554001200,
            "dt_txt": "2019-03-31 03:00:00",
            "main": {
                "grnd_level": 1011.07,
                "humidity": 100,
                "pressure": 1023.939,
                "sea_level": 1023.939,
                "temp": 286.582,
                "temp_kf": 0,
                "temp_max": 286.582,
                "temp_min": 286.582
            },
            "sys": {
                "pod": "n"
            },
            "weather": [
                {
                    "description": "few clouds",
                    "icon": "02n",
                    "id": 801,
                    "main": "Clouds"
                }
            ],
            "wind": {
                "deg": 295.458,
                "speed": 3.12
            }
        },
        {
            "clouds": {
                "all": 12
            },
            "dt": 1554004800,
            "dt_txt": "2019-03-31 04:00:00",
            "main": {
                "grnd_level": 1011.742,
                "humidity": 100,
                "pressure": 1024.588,
                "sea_level": 1024.588,
                "temp": 285.933,
                "temp_kf": 0,
                "temp_max": 285.933,
                "temp_min": 285.933
            },
            "sys": {
                "pod": "n"
            },
            "weather": [
                {
                    "description": "few clouds",
                    "icon": "02n",
                    "id": 801,
                    "main": "Clouds"
                }
            ],
            "wind": {
                "deg": 298.184,
                "speed": 2.53
            }
        },
        {
            "clouds": {
                "all": 10
            },
            "dt": 1554008400,
            "dt_txt": "2019-03-31 05:00:00",
            "main": {
                "grnd_level": 1011.966,
                "humidity": 100,
                "pressure": 1024.987,
                "sea_level": 1024.987,
                "temp": 285.5,
                "temp_kf": 0,
                "temp_max": 285.5,
                "temp_min": 285.5
            },
            "sys": {
                "pod": "n"
            },
            "weather": [
                {
                    "description": "clear sky",
                    "icon": "02n",
                    "id": 800,
                    "main": "Clear"
                }
            ],
            "wind": {
                "deg": 299.586,
                "speed": 1.52
            }
        },
        {
            "clouds": {
                "all": 12
            },
            "dt": 1554012000,
            "dt_txt": "2019-03-31 06:00:00",
            "main": {
                "grnd_level": 1011.704,
                "humidity": 100,
                "pressure": 1024.93,
                "sea_level": 1024.93,
                "temp": 285.152,
                "temp_kf": 0,
                "temp_max": 285.152,
                "temp_min": 285.152
            },
            "sys": {
                "pod": "n"
            },
            "weather": [
                {
                    "description": "few clouds",
                    "icon": "02n",
                    "id": 801,
                    "main": "Clouds"
                }
            ],
            "wind": {
                "deg": 288.747,
                "speed": 1.11
            }
        },
        {
            "clouds": {
                "all": 39
            },
            "dt": 1554015600,
            "dt_txt": "2019-03-31 07:00:00",
            "main": {
                "grnd_level": 1011.521,
                "humidity": 100,
                "pressure": 1024.641,
                "sea_level": 1024.641,
                "temp": 284.977,
                "temp_kf": 0,
                "temp_max": 284.977,
                "temp_min": 284.977
            },
            "sys": {
                "pod": "n"
            },
            "weather": [
                {
                    "description": "scattered clouds",
                    "icon": "03n",
                    "id": 802,
                    "main": "Clouds"
                }
            ],
            "wind": {
                "deg": 288.85,
                "speed": 1.48
            }
        },
        {
            "clouds": {
                "all": 47
            },
            "dt": 1554019200,
            "dt_txt": "2019-03-31 08:00:00",
            "main": {
                "grnd_level": 1011.302,
                "humidity": 100,
                "pressure": 1024.529,
                "sea_level": 1024.529,
                "temp": 284.733,
                "temp_kf": 0,
                "temp_max": 284.733,
                "temp_min": 284.733
            },
            "sys": {
                "pod": "n"
            },
            "weather": [
                {
                    "description": "scattered clouds",
                    "icon": "03n",
                    "id": 802,
                    "main": "Clouds"
                }
            ],
            "wind": {
                "deg": 297.705,
                "speed": 1.1
            }
        },
        {
            "clouds": {
                "all": 54
            },
            "dt": 1554022800,
            "dt_txt": "2019-03-31 09:00:00",
            "main": {
                "grnd_level": 1011.156,
                "humidity": 100,
                "pressure": 1024.47,
                "sea_level": 1024.47,
                "temp": 284.506,
                "temp_kf": 0,
                "temp_max": 284.506,
                "temp_min": 284.506
            },
            "sys": {
                "pod": "n"
            },
            "weather": [
                {
                    "description": "broken clouds",
                    "icon": "04n",
                    "id": 803,
                    "main": "Clouds"
                }
            ],
            "wind": {
                "deg": 304.531,
                "speed": 1.06
            }
        },
        {
            "clouds": {
                "all": 61
            },
            "dt": 1554026400,
            "dt_txt": "2019-03-31 10:00:00",
            "main": {
                "grnd_level": 1010.949,
                "humidity": 100,
                "pressure": 1024.318,
                "sea_level": 1024.318,
                "temp": 284.368,
                "temp_kf": 0,
                "temp_max": 284.368,
                "temp_min": 284.368
            },
            "sys": {
                "pod": "n"
            },
            "weather": [
                {
                    "description": "broken clouds",
                    "icon": "04n",
                    "id": 803,
                    "main": "Clouds"
                }
            ],
            "wind": {
                "deg": 313.937,
                "speed": 1.11
            }
        },
        {
            "clouds": {
                "all": 63
            },
            "dt": 1554030000,
            "dt_txt": "2019-03-31 11:00:00",
            "main": {
                "grnd_level": 1010.773,
                "humidity": 100,
                "pressure": 1024.172,
                "sea_level": 1024.172,
                "temp": 284.2,
                "temp_kf": 0,
                "temp_max": 284.2,
                "temp_min": 284.2
            },
            "sys": {
                "pod": "n"
            },
            "weather": [
                {
                    "description": "broken clouds",
                    "icon": "04n",
                    "id": 803,
                    "main": "Clouds"
                }
            ],
            "wind": {
                "deg": 323.47,
                "speed": 1.11
            }
        },
        {
            "clouds": {
                "all": 60
            },
            "dt": 1554033600,
            "dt_txt": "2019-03-31 12:00:00",
            "main": {
                "grnd_level": 1010.753,
                "humidity": 100,
                "pressure": 1024.132,
                "sea_level": 1024.132,
                "temp": 284.083,
                "temp_kf": 0,
                "temp_max": 284.083,
                "temp_min": 284.083
            },
            "sys": {
                "pod": "n"
            },
            "weather": [
                {
                    "description": "broken clouds",
                    "icon": "04n",
                    "id": 803,
                    "main": "Clouds"
                }
            ],
            "wind": {
                "deg": 330.631,
                "speed": 1.13
            }
        },
        {
            "clouds": {
                "all": 43
            },
            "dt": 1554037200,
            "dt_txt": "2019-03-31 13:00:00",
            "main": {
                "grnd_level": 1010.717,
                "humidity": 100,
                "pressure": 1024.121,
                "sea_level": 1024.121,
                "temp": 283.921,
                "temp_kf": 0,
                "temp_max": 283.921,
                "temp_min": 283.921
            },
            "sys": {
                "pod": "n"
            },
            "weather": [
                {
                    "description": "scattered clouds",
                    "icon": "03n",
                    "id": 802,
                    "main": "Clouds"
                }
            ],
            "wind": {
                "deg": 349.952,
                "speed": 1
            }
        },
        {
            "clouds": {
                "all": 45
            },
            "dt": 1554040800,
            "dt_txt": "2019-03-31 14:00:00",
            "main": {
                "grnd_level": 1010.794,
                "humidity": 100,
                "pressure": 1024.185,
                "sea_level": 1024.185,
                "temp": 283.835,
                "temp_kf": 0,
                "temp_max": 283.835,
                "temp_min": 283.835
            },
            "sys": {
                "pod": "d"
            },
            "weather": [
                {
                    "description": "scattered clouds",
                    "icon": "03d",
                    "id": 802,
                    "main": "Clouds"
                }
            ],
            "wind": {
                "deg": 355.835,
                "speed": 0.92
            }
        },
        {
            "clouds": {
                "all": 47
            },
            "dt": 1554044400,
            "dt_txt": "2019-03-31 15:00:00",
            "main": {
                "grnd_level": 1010.99,
                "humidity": 100,
                "pressure": 1024.272,
                "sea_level": 1024.272,
                "temp": 285.1,
                "temp_kf": 0,
                "temp_max": 285.1,
                "temp_min": 285.1
            },
            "sys": {
                "pod": "d"
            },
            "weather": [
                {
                    "description": "scattered clouds",
                    "icon": "03d",
                    "id": 802,
                    "main": "Clouds"
                }
            ],
            "wind": {
                "deg": 352.222,
                "speed": 0.97
            }
        },
        {
            "clouds": {
                "all": 44
            },
            "dt": 1554048000,
            "dt_txt": "2019-03-31 16:00:00",
            "main": {
                "grnd_level": 1011.159,
                "humidity": 100,
                "pressure": 1024.177,
                "sea_level": 1024.177,
                "temp": 286.995,
                "temp_kf": 0,
                "temp_max": 286.995,
                "temp_min": 286.995
            },
            "sys": {
                "pod": "d"
            },
            "weather": [
                {
                    "description": "scattered clouds",
                    "icon": "03d",
                    "id": 802,
                    "main": "Clouds"
                }
            ],
            "wind": {
                "deg": 337.56,
                "speed": 1.35
            }
        },
        {
            "clouds": {
                "all": 50
            },
            "dt": 1554051600,
            "dt_txt": "2019-03-31 17:00:00",
            "main": {
                "grnd_level": 1011.112,
                "humidity": 100,
                "pressure": 1023.992,
                "sea_level": 1023.992,
                "temp": 288.9,
                "temp_kf": 0,
                "temp_max": 288.9,
                "temp_min": 288.9
            },
            "sys": {
                "pod": "d"
            },
            "weather": [
                {
                    "description": "scattered clouds",
                    "icon": "03d",
                    "id": 802,
                    "main": "Clouds"
                }
            ],
            "wind": {
                "deg": 347.482,
                "speed": 1.69
            }
        }
    ],
    "message": 0.0208
}